gfpgan/__init__.py
gfpgan/train.py
gfpgan/utils.py
gfpgan/version.py
gfpgan/archs/__init__.py
gfpgan/archs/arcface_arch.py
gfpgan/archs/gfpgan_bilinear_arch.py
gfpgan/archs/gfpganv1_arch.py
gfpgan/archs/gfpganv1_clean_arch.py
gfpgan/archs/restoreformer_arch.py
gfpgan/archs/stylegan2_bilinear_arch.py
gfpgan/archs/stylegan2_clean_arch.py
gfpgan/data/__init__.py
gfpgan/data/ffhq_degradation_dataset.py
gfpgan/models/__init__.py
gfpgan/models/gfpgan_model.py
gfpgan/weights/README.md
new_gfpgan-1.0.1.dist-info/LICENSE
new_gfpgan-1.0.1.dist-info/METADATA
new_gfpgan-1.0.1.dist-info/WHEEL
new_gfpgan-1.0.1.dist-info/top_level.txt
new_gfpgan-1.0.1.dist-info/RECORD
